odoo/addons/l10n_ro_config/README.rst
odoo/addons/l10n_ro_config/__init__.py
odoo/addons/l10n_ro_config/__manifest__.py
odoo/addons/l10n_ro_config/i18n/l10n_ro_config.pot
odoo/addons/l10n_ro_config/models/__init__.py
odoo/addons/l10n_ro_config/models/res_bank.py
odoo/addons/l10n_ro_config/models/res_company.py
odoo/addons/l10n_ro_config/models/res_config_settings.py
odoo/addons/l10n_ro_config/models/res_partner.py
odoo/addons/l10n_ro_config/readme/CONTRIBUTORS.rst
odoo/addons/l10n_ro_config/readme/DESCRIPTION.rst
odoo/addons/l10n_ro_config/static/description/icon.png
odoo/addons/l10n_ro_config/static/description/icon.svg
odoo/addons/l10n_ro_config/static/description/index.html
odoo/addons/l10n_ro_config/tests/__init__.py
odoo/addons/l10n_ro_config/tests/test_partner_country_code.py
odoo/addons/l10n_ro_config/views/common_report.xml
odoo/addons/l10n_ro_config/views/res_bank_view.xml
odoo/addons/l10n_ro_config/views/res_config_view.xml
odoo/addons/l10n_ro_config/views/res_partner_view.xml
odoo13_addon_l10n_ro_config-13.0.1.1.0.dist-info/METADATA
odoo13_addon_l10n_ro_config-13.0.1.1.0.dist-info/WHEEL
odoo13_addon_l10n_ro_config-13.0.1.1.0.dist-info/top_level.txt
odoo13_addon_l10n_ro_config-13.0.1.1.0.dist-info/RECORD
